kipio/__init__.py
kipio/kipio.py
kipio-1.0.0.dist-info/licenses/LICENSE
kipio-1.0.0.dist-info/METADATA
kipio-1.0.0.dist-info/WHEEL
kipio-1.0.0.dist-info/top_level.txt
kipio-1.0.0.dist-info/RECORD
