Metadata-Version: 2.4
Name: kipio
Version: 1.0.0
Summary: Enhanced I/O Library for Python
Author-email: kiux-tools <gg2018177@gmail.com>
License: MIT
Project-URL: Homepage, https://github.com/kiux-tools/kipio
Project-URL: Documentation, https://github.com/kiux-tools/kipio#readme
Project-URL: Repository, https://github.com/kiux-tools/kipio
Project-URL: Issues, https://github.com/kiux-tools/kipio/issues
Project-URL: Changelog, https://github.com/kiux-tools/kipio/releases
Keywords: io,input,output,cli,utilities,enhanced,user-input,file-io,terminal,kipio,kiux-tools,python-io,console
Classifier: Development Status :: 5 - Production/Stable
Classifier: Intended Audience :: Developers
Classifier: Topic :: Software Development :: Libraries :: Python Modules
Classifier: License :: OSI Approved :: MIT License
Classifier: Programming Language :: Python :: 3
Classifier: Programming Language :: Python :: 3 :: Only
Classifier: Programming Language :: Python :: 3.7
Classifier: Programming Language :: Python :: 3.8
Classifier: Programming Language :: Python :: 3.9
Classifier: Programming Language :: Python :: 3.10
Classifier: Programming Language :: Python :: 3.11
Classifier: Programming Language :: Python :: 3.12
Classifier: Operating System :: OS Independent
Requires-Python: >=3.7
License-File: LICENSE
Provides-Extra: test
Requires-Dist: pytest>=7.0.0; extra == "test"
Requires-Dist: pytest-cov>=4.0.0; extra == "test"
Provides-Extra: dev
Requires-Dist: pytest>=7.0.0; extra == "dev"
Requires-Dist: pytest-cov>=4.0.0; extra == "dev"
Requires-Dist: black>=23.0.0; extra == "dev"
Requires-Dist: flake8>=6.0.0; extra == "dev"
Dynamic: license-file
